scramp/__init__.py
scramp/core.py
scramp/utils.py
scramp-1.4.3.dist-info/LICENSE
scramp-1.4.3.dist-info/METADATA
scramp-1.4.3.dist-info/WHEEL
scramp-1.4.3.dist-info/top_level.txt
scramp-1.4.3.dist-info/RECORD
